openvpn_management_api/__init__.py
openvpn_management_api/constants.py
openvpn_management_api/vpn.py
openvpn_management_api/events/__init__.py
openvpn_management_api/events/base.py
openvpn_management_api/events/client.py
openvpn_management_api/events/updown.py
openvpn_management_api/models/__init__.py
openvpn_management_api/models/state.py
openvpn_management_api/models/stats.py
openvpn_management_api/util/__init__.py
openvpn_management_api/util/errors.py
openvpn_management_api/util/logging.py
openvpn_management_api/util/parsing.py
openvpn_management_api-0.4.0.dist-info/licenses/LICENSE
openvpn_management_api-0.4.0.dist-info/METADATA
openvpn_management_api-0.4.0.dist-info/WHEEL
openvpn_management_api-0.4.0.dist-info/top_level.txt
openvpn_management_api-0.4.0.dist-info/RECORD
