Metadata-Version: 2.4
Name: openvpn-management-api
Version: 0.4.0
Summary: A revised Python API for the OpenVPN management interface.
Author-email: "M. Hosseyn Najafi" <hosseynjf@icloud.com>
Project-URL: Source, https://github.com/HosseyNJF/openvpn-management-api
Project-URL: Bug Reports, https://github.com/HosseyNJF/openvpn-management-api/issues
Project-URL: Homepage, https://github.com/HosseyNJF/openvpn-management-api
Keywords: openvpn,monitor,management,api
Classifier: Development Status :: 3 - Alpha
Classifier: Intended Audience :: Developers
Classifier: Intended Audience :: System Administrators
Classifier: Operating System :: OS Independent
Classifier: Programming Language :: Python :: 3.6
Classifier: Programming Language :: Python :: 3.7
Classifier: Programming Language :: Python :: 3.8
Classifier: Programming Language :: Python :: 3.9
Classifier: Programming Language :: Python :: 3.10
Classifier: Programming Language :: Python :: 3.11
Classifier: Programming Language :: Python :: 3.12
Classifier: Programming Language :: Python :: 3.13
Requires-Python: >=3.6
License-File: LICENSE
Requires-Dist: openvpn_status<1.0.0
Provides-Extra: dev
Requires-Dist: nose; extra == "dev"
Requires-Dist: black; extra == "dev"
Dynamic: license-file
